README.md
setup.py
strappy/__init__.py
strappy.egg-info/PKG-INFO
strappy.egg-info/SOURCES.txt
strappy.egg-info/dependency_links.txt
strappy.egg-info/top_level.txt
strappy/monitoring/__init__.py
strappy/monitoring/psi.py
strappy/style/__init__.py
strappy/style/styles.py
strappy/transformers/__init__.py
strappy/transformers/_base.py
strappy/transformers/_categorical_binners.py
strappy/transformers/_experimental.py
strappy/transformers/_numeric_transformers.py
strappy/transformers/_text_vectorizer.py
strappy/transformers/_transform_wrapper.py
strappy/transformers/_variable_selector.py
strappy/utils/__init__.py
strappy/utils/binners.py
strappy/utils/dates.py
strappy/utils/formatters.py
strappy/utils/histograms.py
strappy/utils/stats.py
tests/__init__.py
tests/test_binners.py
tests/test_categorical.py
tests/test_column_selector.py
tests/test_dates.py
tests/test_histograms.py
tests/test_numeric_transformers.py
tests/test_psi.py
tests/test_text_vectorizer.py